image_fetcher/__init__.py
image_fetcher/download_images.py
image_fetcher/tools.py
tests/__init__.py
tests/test_download_images.py
tests/test_tools.py
image_fetcher-2.0.1.dist-info/LICENSE
image_fetcher-2.0.1.dist-info/METADATA
image_fetcher-2.0.1.dist-info/WHEEL
image_fetcher-2.0.1.dist-info/top_level.txt
image_fetcher-2.0.1.dist-info/RECORD
