Metadata-Version: 2.1
Name: image-fetcher
Version: 2.0.1
Summary: A simple lightweight library to download images (and other files)
Home-page: https://github.com/BenAAndrew/Python-Image-Fetcher
Author: Ben Andrew
Author-email: benandrew89@gmail.com
License: UNKNOWN
Platform: UNKNOWN
Classifier: Programming Language :: Python :: 3
Classifier: License :: OSI Approved :: MIT License
Classifier: Operating System :: OS Independent
Requires-Python: >=3.5
License-File: LICENSE
Requires-Dist: func-timeout (==4.3.5)
Requires-Dist: tqdm (==4.62.0)
Requires-Dist: urllib3 (==1.26.6)
